jexpand/__init__.py
jexpand/__main__.py
jexpand/load_from_repo.py
jexpand/main.py
jexpand/shorthand_parser.py
tests/run_all_tests.py
tests/01_core_functions/include_file/test_runner.py
tests/01_core_functions/include_folder/sample_folder/file1.py
tests/02_template_filters/code_block/sample_code.py
tests/06_cli_features/test_clipboard.py
tests/08_shorthand_parser/test_shorthand_parser.py
jexpand-1.0.11.dist-info/METADATA
jexpand-1.0.11.dist-info/WHEEL
jexpand-1.0.11.dist-info/entry_points.txt
jexpand-1.0.11.dist-info/top_level.txt
jexpand-1.0.11.dist-info/RECORD
